{
  "fit_id": "glob_all_lin_5c",
  "mode": "nn",
  "process": "tt",
  "order": "lin",
  "nlive": 500,
  "results_path": "/data/theorie/jthoeve/ns_samples/tt_llvlvlbb",
  "lumi": 3e5,
  "observed_data_path": "/data/theorie/jthoeve/ML4EFT_jan/ML4EFT/observed_data/tt_llvlvlbb_sm/events_0.pkl.gz",
  "bins": {
    "pt_ll": [
      0,
      10,
      20,
      40,
      60,
      100,
      150,
      400,
      10000
    ],
    "eta_l1": [
      -2.5,
      -2.1,
      -1.8,
      -1.5,
      -1.2,
      -0.9,
      -0.6,
      -0.3,
      0,
      0.3,
      0.6,
      0.9,
      1.2,
      1.5,
      1.8,
      2.1,
      2.5
    ]
  },
  "path_to_models": "/data/theorie/jthoeve/ML4EFT_jan/ML4EFT/models/tt_llvlvlbb/2022/09/12",
  "path_to_theory_pred": "/data/theorie/jthoeve/ML4EFT_jan/ML4EFT/training_data/tt_llvlvlbb",
  "prior": {
    "ctGRe": [
      -2,
      2
    ],
    "cQj18": [
      -2,
      2
    ],
    "ctj8": [
      -2,
      2
    ],
    "cQu8": [
      -2,
      2
    ],
    "cQd8": [
      -2,
      2
    ],
    "ctd8": [
      -2,
      2
    ],
    "cQj38": [
      -2,
      2
    ],
    "ctu8": [
      -2,
      2
    ]
  },
  "th_features": [
    "y",
    "m_tt",
    "pt_t"
  ]
}